steganography_tools/__init__.py
steganography_tools/image_processing.py
steganography_tools/rsa_text_encoding.py
steganography_tools/st.py
steganography_tools-0.1.5.dist-info/entry_points.txt
steganography_tools-0.1.5.dist-info/LICENSE
steganography_tools-0.1.5.dist-info/WHEEL
steganography_tools-0.1.5.dist-info/METADATA
steganography_tools-0.1.5.dist-info/RECORD
