Metadata-Version: 2.1
Name: steganography-tools
Version: 0.1.5
Summary: A Python library for higher level python functions used in image analysis and computer vision for steganography
Home-page: https://github.com/sebastienmascha/data-science-package-steganography-tools
License: MIT
Keywords: steganography,computer-vision,image,encoding
Author: Sebastien Mascha
Author-email: sebastien.mascha@gmail.com
Requires-Python: >=3.7,<4.0
Classifier: License :: OSI Approved :: MIT License
Classifier: Programming Language :: Python :: 3
Classifier: Programming Language :: Python :: 3.7
Classifier: Programming Language :: Python :: 3.8
Classifier: Programming Language :: Python :: 3.9
Requires-Dist: Pillow (>=8.2.0,<9.0.0)
Requires-Dist: numpy (>=1.18,<1.20)
Requires-Dist: pycryptodome (>=3.10.1,<4.0.0)
Project-URL: Repository, https://github.com/sebastienmascha/data-science-package-steganography-tools
